<level>
<description>You now have access to the &lt;color=#ffff00ff&gt;PRINTER&lt;/color&gt; tool.
The &lt;color=#ffff00ff&gt;PRINTER&lt;/color&gt; will print output if you use it on &lt;color=#ffff00ff&gt;yellow&lt;/color&gt; text.
Use the BUGCATCHER to catch the bug once you know where it is.
You can use TAB to switch between tools.</description>
<next-level>tut2.xml</next-level>
<introtext>Time to learn a new tool: 
&lt;color=#ffff00ff&gt;PRINTERS&lt;/color&gt;.
They can show you output from the code.</introtext>
<endtext>Now it's your turn,
use the &lt;color=#ffff00ff&gt;PRINTERS&lt;/color&gt;!</endtext>
<timelimit>1000</timelimit>
<tools>
<tool name="printer" enabled="true" count="unlimited"/>
<tool name="catcher" enabled="true" count="unlimited"/>
</tools>
<code language="c++">void FCalls(string errmsg){                        
    //call some functions then return								 @We can use print statements to help us investigate the bug. The Printer tool will give us information.@
	<print text="$err$function2: Index out of Range" col="4">cout &lt;&lt; errmsg;</print>                   @Let's see what the error message says!@ ??? !!!
	function1();                    
	$bug$function2();    @It looks like the error is in this function.@ ??? !!!
	function3();
    function4();
	function5();
    return;
}
</code>
</level>